setup.cfg
setup.py
renren/__init__.py
renren/renren.py
renren.egg-info/PKG-INFO
renren.egg-info/SOURCES.txt
renren.egg-info/dependency_links.txt
renren.egg-info/entry_points.txt
renren.egg-info/top_level.txt
renren.egg-info/zip-safe