Metadata-Version: 1.0
Name: renren
Version: 1.0dev
Summary: renren python sdk
Home-page: http://yaofan.9miao.com/other/1
Author: lanjinmin
Author-email: 463473243@qq.com
License: UNKNOWN
Keywords: renren sdk
Platform: UNKNOWN
